MANIFEST.in
README.md
default.txt
setup.cfg
setup.py
micro_ussd_airflow_engine.egg-info/PKG-INFO
micro_ussd_airflow_engine.egg-info/SOURCES.txt
micro_ussd_airflow_engine.egg-info/dependency_links.txt
micro_ussd_airflow_engine.egg-info/requires.txt
micro_ussd_airflow_engine.egg-info/top_level.txt
ussd/__init__.py
ussd/apis.py
ussd/apps.py
ussd/built_in_functions.py
ussd/core.py
ussd/defaults.py
ussd/django_view.py
ussd/exceptions.py
ussd/graph.py
ussd/models.py
ussd/session_store.py
ussd/tasks.py
ussd/urls.py
ussd/utilities.py
ussd/version.py
ussd/views.py
ussd/filters/__init__.py
ussd/filters/date_filters.py
ussd/filters/dict_filters.py
ussd/filters/list_filters.py
ussd/filters/utility_filters.py
ussd/migrations/0001_initial.py
ussd/migrations/__init__.py
ussd/screens/__init__.py
ussd/screens/custom_screen.py
ussd/screens/function_screen.py
ussd/screens/http_screen.py
ussd/screens/initial_screen.py
ussd/screens/input_screen.py
ussd/screens/menu_screen.py
ussd/screens/quit_screen.py
ussd/screens/router_screen.py
ussd/screens/serializers.py
ussd/screens/update_session_screen.py
ussd/store/__init__.py
ussd/store/journey_store.py
ussd/store/journey_store/DummyStore.py
ussd/store/journey_store/DynamoDb.py
ussd/store/journey_store/YamlJourneyStore.py
ussd/store/journey_store/__init__.py
ussd/store/journey_store/tests/__init__.py
ussd/store/journey_store/tests/test_store.py
ussd/tests/__init__.py
ussd/tests/test_built_in_functions.py
ussd/tests/test_core_functionaliyt.py
ussd/tests/test_custom_screen.py
ussd/tests/test_date_filters.py
ussd/tests/test_function_screen.py
ussd/tests/test_graph.py
ussd/tests/test_http_screen.py
ussd/tests/test_initial_screen.py
ussd/tests/test_input_screen.py
ussd/tests/test_list_screen.py
ussd/tests/test_menu_screen.py
ussd/tests/test_multi_language_support_from_session_data.py
ussd/tests/test_quit_screen.py
ussd/tests/test_report_session.py
ussd/tests/test_router_screen.py
ussd/tests/test_session_store.py
ussd/tests/test_update_session_screen.py
ussd/tests/test_ussd_interaction.py
ussd/tests/test_utility_filters.py
ussd/tests/test_variables.py
ussd/tests/test_yaml_include_simple.py
ussd/tests/utils.py
ussd/tests/sample_screen_definition/__init__.py
