Metadata-Version: 1.1
Name: micro-ussd-airflow-engine
Version: 0.1.2
Summary: Micro Ussd Engine Airflow Library
Home-page: https://github.com/seidu626/ussd_engine
Author: Seidu
Author-email: seidu.abdulai@hotmail.com
License: MIT
Download-URL: https://github.com/seidu626/ussd_engine/archive/v0.1.tar.gz
Keywords: USSD,GATEWAY
Platform: UNKNOWN
Classifier: Development Status :: 3 - Alpha
Classifier: Intended Audience :: Developers
Classifier: Topic :: Software Development :: Build Tools
Classifier: License :: OSI Approved :: MIT License
Classifier: Programming Language :: Python :: 3
Classifier: Programming Language :: Python :: 3.4
Classifier: Programming Language :: Python :: 3.5
Classifier: Programming Language :: Python :: 3.6
Classifier: Programming Language :: Python :: 3.7
Classifier: Programming Language :: Python :: 3.8
